LICENSE
MANIFEST.in
README.md
requirements.txt
setup.py
joker/filesys/__init__.py
joker/filesys/archives.py
joker/filesys/cas.py
joker/filesys/dirs.py
joker/filesys/git.py
joker/filesys/utils.py
joker_filesys.egg-info/PKG-INFO
joker_filesys.egg-info/SOURCES.txt
joker_filesys.egg-info/dependency_links.txt
joker_filesys.egg-info/namespace_packages.txt
joker_filesys.egg-info/not-zip-safe
joker_filesys.egg-info/requires.txt
joker_filesys.egg-info/top_level.txt
tests/test_filesys.py
tests/test_imports.py